docx_renderer/__init__.py
docx_renderer/command_line.py
docx_renderer/docx_renderer.py
docx_renderer/exceptions.py
docx_renderer/plugins.py
docx_renderer/utils.py
docx_renderer-0.3.0.dist-info/licenses/LICENSE
docx_renderer-0.3.0.dist-info/METADATA
docx_renderer-0.3.0.dist-info/WHEEL
docx_renderer-0.3.0.dist-info/entry_points.txt
docx_renderer-0.3.0.dist-info/top_level.txt
docx_renderer-0.3.0.dist-info/RECORD
