Metadata-Version: 2.4
Name: docx_renderer
Version: 0.3.0
Summary: Create Microsoft word documents from templates
Author-email: Najeem Muhammed <najeem@gmail.com>
License: MIT License
Project-URL: Homepage, https://github.com/idling-mind/docx_renderer
Project-URL: Bug Tracker, https://github.com/idling-mind/docx_renderer/issues
Keywords: microsoft,word,doc,docx,document,pages,report
Classifier: Programming Language :: Python :: 3
Classifier: License :: OSI Approved :: MIT License
Classifier: Operating System :: OS Independent
Requires-Python: >=3.8
License-File: LICENSE
Requires-Dist: python-docx>=1.1.0
Requires-Dist: click
Requires-Dist: Pillow>=9.3
Provides-Extra: test
Requires-Dist: pytest; extra == "test"
Requires-Dist: coverage; extra == "test"
Dynamic: license-file
